acanban/__init__.py
acanban/__main__.py
acanban/auth.py
acanban/config.py
acanban/db.py
acanban/ipfs.py
acanban/project.py
acanban/py.typed
acanban/task.py
acanban/user.py
acanban/static/android-chrome-192x192.png
acanban/static/android-chrome-512x512.png
acanban/static/apple-touch-icon.png
acanban/static/collaboration.svg
acanban/static/dropdown-icon.svg
acanban/static/favicon-16x16.png
acanban/static/favicon-32x32.png
acanban/static/favicon.ico
acanban/static/site.webmanifest
acanban/static/style.css
acanban/templates/base.html
acanban/templates/index.html
acanban/templates/login.html
acanban/templates/myproject.html
acanban/templates/project-create.html
acanban/templates/project-edit.html
acanban/templates/project-info.html
acanban/templates/project-list.html
acanban/templates/project-members.html
acanban/templates/project-report.html
acanban/templates/project-slides.html
acanban/templates/project-tab.html
acanban/templates/project-tasks.html
acanban/templates/register.html
acanban/templates/task-create.html
acanban/templates/task.html
acanban/templates/user-edit.html
acanban/templates/user.html
acanban-0.1.3.dist-info/LICENSE
acanban-0.1.3.dist-info/WHEEL
acanban-0.1.3.dist-info/METADATA
acanban-0.1.3.dist-info/RECORD
