Metadata-Version: 2.1
Name: acanban
Version: 0.1.3
Summary: Academic Kanban
Home-page: https://Huy-Ngo.github.io/acanban
License: AGPLv3+
Keywords: academic,kanban
Author: Ngô Ngọc Đức Huy
Author-email: duchuy29092000@gmail.com
Requires-Python: >=3.7
Classifier: Development Status :: 3 - Alpha
Classifier: Environment :: Web Environment
Classifier: Framework :: Trio
Classifier: Intended Audience :: Education
Classifier: Intended Audience :: End Users/Desktop
Classifier: License :: OSI Approved :: GNU Affero General Public License v3 or later (AGPLv3+)
Classifier: Natural Language :: English
Classifier: Operating System :: POSIX
Classifier: Programming Language :: Python :: 3 :: Only
Classifier: Programming Language :: Python :: 3.7
Classifier: Programming Language :: Python :: 3.8
Classifier: Programming Language :: Python :: 3.9
Classifier: Topic :: Education
Classifier: Typing :: Typed
Requires-Dist: appdirs
Requires-Dist: bleach
Requires-Dist: bleach_allowlist
Requires-Dist: httpx
Requires-Dist: humanize
Requires-Dist: hypercorn
Requires-Dist: markdown
Requires-Dist: py-cid
Requires-Dist: quart-auth
Requires-Dist: quart-trio-twice
Requires-Dist: rethinkdb >=2.4.8
